README.rst
setup.cfg
setup.py
./__init__.py
./invoice.py
./invoice.xml
./tryton.cfg
./tests/__init__.py
./tests/test_invoice.py
./tests/test_views_depends.py
./view/invoice_form.xml
./view/pay_using_transaction_start_form.xml
openlabs_invoice_payment_gateway.egg-info/PKG-INFO
openlabs_invoice_payment_gateway.egg-info/SOURCES.txt
openlabs_invoice_payment_gateway.egg-info/dependency_links.txt
openlabs_invoice_payment_gateway.egg-info/entry_points.txt
openlabs_invoice_payment_gateway.egg-info/not-zip-safe
openlabs_invoice_payment_gateway.egg-info/requires.txt
openlabs_invoice_payment_gateway.egg-info/top_level.txt